intoyuniot-3.4.4.dist-info/DESCRIPTION.rst
intoyuniot-3.4.4.dist-info/METADATA
intoyuniot-3.4.4.dist-info/RECORD
intoyuniot-3.4.4.dist-info/WHEEL
intoyuniot-3.4.4.dist-info/entry_points.txt
intoyuniot-3.4.4.dist-info/metadata.json
intoyuniot-3.4.4.dist-info/top_level.txt
platformio/__init__.py
platformio/__main__.py
platformio/app.py
platformio/downloader.py
platformio/exception.py
platformio/maintenance.py
platformio/projectconftpl.ini
platformio/telemetry.py
platformio/unpacker.py
platformio/util.py
platformio/vcsclient.py
platformio/builder/__init__.py
platformio/builder/main.py
platformio/builder/tools/__init__.py
platformio/builder/tools/pioide.py
platformio/builder/tools/piolib.py
platformio/builder/tools/piomisc.py
platformio/builder/tools/pioplatform.py
platformio/builder/tools/pioupload.py
platformio/builder/tools/piowinhooks.py
platformio/builder/tools/platformio.py
platformio/commands/__init__.py
platformio/commands/boards.py
platformio/commands/ci.py
platformio/commands/device.py
platformio/commands/init.py
platformio/commands/lib.py
platformio/commands/platform.py
platformio/commands/run.py
platformio/commands/settings.py
platformio/commands/test.py
platformio/commands/update.py
platformio/commands/upgrade.py
platformio/ide/__init__.py
platformio/ide/projectgenerator.py
platformio/ide/tpls/atom/.clang_complete.tpl
platformio/ide/tpls/atom/.gcc-flags.json.tpl
platformio/ide/tpls/atom/.gitignore.tpl
platformio/ide/tpls/clion/.gitignore.tpl
platformio/ide/tpls/clion/CMakeLists.txt.tpl
platformio/ide/tpls/clion/CMakeListsPrivate.txt.tpl
platformio/ide/tpls/clion/.idea/clion.iml.tpl
platformio/ide/tpls/clion/.idea/modules.xml.tpl
platformio/ide/tpls/clion/.idea/platformio.iml.tpl
platformio/ide/tpls/clion/.idea/watcherTasks.xml.tpl
platformio/ide/tpls/clion/.idea/workspace.xml.tpl
platformio/ide/tpls/codeblocks/platformio.cbp.tpl
platformio/ide/tpls/eclipse/.cproject.tpl
platformio/ide/tpls/eclipse/.project.tpl
platformio/ide/tpls/eclipse/.settings/PlatformIO Debugger.launch.tpl
platformio/ide/tpls/eclipse/.settings/language.settings.xml.tpl
platformio/ide/tpls/eclipse/.settings/org.eclipse.cdt.core.prefs.tpl
platformio/ide/tpls/emacs/.clang_complete.tpl
