Metadata-Version: 2.0
Name: intoyuniot
Version: 3.4.4
Summary: An open source tools for IntoYun IoT development. Cross-platform build system and library manager. Continuous and IDE integration. Arduino, ESP8266 and ARM mbed compatible
Home-page: https://dl.intoyun.com/
Author: Robin chen
Author-email: robin@molmc.com
License: Apache Software License
Keywords: iot,embedded,arduino,mbed,esp8266,esp32,fpga,firmware,continuous-integration,cloud-ide,avr,arm,ide,unit-testing,hardware,verilog,microcontroller,debug
Platform: UNKNOWN
Classifier: Development Status :: 5 - Production/Stable
Classifier: Environment :: Console
Classifier: Intended Audience :: Developers
Classifier: License :: OSI Approved :: Apache Software License
Classifier: Operating System :: OS Independent
Classifier: Programming Language :: C
Classifier: Programming Language :: Python
Classifier: Topic :: Software Development
Classifier: Topic :: Software Development :: Build Tools
Classifier: Topic :: Software Development :: Compilers
Requires-Dist: arrow (<1)
Requires-Dist: bottle (<0.13)
Requires-Dist: click (>=5,<6)
Requires-Dist: colorama
Requires-Dist: lockfile (<0.13,>=0.9.1)
Requires-Dist: pyserial (!=3.3,>=3,<4)
Requires-Dist: requests (<3,>=2.4.0)
Requires-Dist: semantic-version (>=2.5.0)
